templateproject/__init__.py
templateproject/command_line.py
templateproject/templateproject.py
templateproject-0.1.dist-info/DESCRIPTION.rst
templateproject-0.1.dist-info/METADATA
templateproject-0.1.dist-info/RECORD
templateproject-0.1.dist-info/WHEEL
templateproject-0.1.dist-info/entry_points.txt
templateproject-0.1.dist-info/metadata.json
templateproject-0.1.dist-info/top_level.txt
