Metadata-Version: 2.0
Name: templateproject
Version: 0.1
Summary: Generate Template Directory Structure for Projects
Home-page: http://github.com/vukovicnikola/templateproject
Author: Nikola Vukovic
Author-email: contact@nikola.me
License: MIT
Platform: UNKNOWN
